<annotation>
	<folder>mesas escolares</folder>
	<filename>mesas escolares_74.jpg</filename>
	<path>/home/gzm-frenzy/Documents/Projects/Object-Counter/simple_images/mesas escolares/mesas escolares_74.jpg</path>
	<source>
		<database>Unknown</database>
	</source>
	<size>
		<width>985</width>
		<height>969</height>
		<depth>3</depth>
	</size>
	<segmented>0</segmented>
	<object>
		<name>m01</name>
		<pose>Unspecified</pose>
		<truncated>0</truncated>
		<difficult>0</difficult>
		<bndbox>
			<xmin>130</xmin>
			<ymin>441</ymin>
			<xmax>882</xmax>
			<ymax>816</ymax>
		</bndbox>
	</object>
</annotation>
